LICENSE
MANIFEST.in
README.md
setup.py
reverseEcology/__init__.py
reverseEcology/graphFunctions.py
reverseEcology/metadataFunctions.py
reverseEcology/sbmlFunctions.py
reverseEcology/seedFunctions.py
reverseEcology.egg-info/PKG-INFO
reverseEcology.egg-info/SOURCES.txt
reverseEcology.egg-info/dependency_links.txt
reverseEcology.egg-info/requires.txt
reverseEcology.egg-info/top_level.txt
reverseEcology/packageData/currencyAminoPairs.txt
reverseEcology/packageData/currencyRemovePairs.txt
reverseEcology/packageData/currencyRemoveSingletons.txt
reverseEcology/packageData/metabMap.csv
reverseEcology/packageData/newChargeDict.txt
reverseEcology/packageData/newFormulaDict.txt