Metadata-Version: 1.1
Name: reverseEcology
Version: 0.5
Summary: Reverse ecology analysis of metabolic network reconstructions
Home-page: https://github.com/joshamilton/reverseEcology
Author: Joshua J. Hamilton
Author-email: joshamilton@gmail.com
License: MIT
Platform: UNKNOWN
Classifier: Development Status :: 3 - Alpha
Classifier: License :: OSI Approved :: MIT License
Classifier: Programming Language :: Python :: 2.7
